tidytuesday/__init__.py
tidytuesday/parse_zip.py
tidytuesday/src.py
tidytuesday-0.1.0.dist-info/LICENSE
tidytuesday-0.1.0.dist-info/METADATA
tidytuesday-0.1.0.dist-info/WHEEL
tidytuesday-0.1.0.dist-info/top_level.txt
tidytuesday-0.1.0.dist-info/RECORD
