Metadata-Version: 2.1
Name: tidytuesday
Version: 0.1.0
Summary: Download #TidyTuesday data
Home-page: https://github.com/ilnaes/tidytuesdaypy
Author: Sean Li
Author-email: seanli646@gmail.com
Classifier: Programming Language :: Python :: 3
Classifier: Programming Language :: Python :: 3.6
Classifier: Programming Language :: Python :: 3.7
Classifier: License :: OSI Approved :: MIT License
Classifier: Operating System :: OS Independent
License-File: LICENSE
Requires-Dist: pandas>=1.0.0
Requires-Dist: PyGithub>=1.54
